layout_detector/__init__.py
layout_detector/extract_pkl.py
layout_detector/layout_runner.py
layout_detector/VGT_model/FeatureMerge.py
layout_detector/VGT_model/VGT.py
layout_detector/VGT_model/VGTTrainerTotal.py
layout_detector/VGT_model/VGTbackbone.py
layout_detector/VGT_model/VGTbeit.py
layout_detector/VGT_model/VGTcheckpointer.py
layout_detector/VGT_model/Wordnn_embedding.py
layout_detector/VGT_model/__init__.py
layout_detector/VGT_model/catalog.py
layout_detector/VGT_model/config.py
layout_detector/VGT_model/defaults.py
layout_detector/VGT_model/ditod_config.py
layout_detector/VGT_model/tokenization_bros.py
layout_detector/VGT_model/checkpoint/__init__.py
layout_detector/VGT_model/checkpoint/c2_model_loading.py
layout_detector/VGT_model/checkpoint/catalog.py
layout_detector/VGT_model/checkpoint/detection_checkpoint.py
layout_detector/VGT_model/data/__init__.py
layout_detector/VGT_model/data/catalog.py
layout_detector/VGT_model/data/common.py
layout_detector/VGT_model/data/detection_utils.py
layout_detector/VGT_model/layers/__init__.py
layout_detector/VGT_model/layers/batch_norm.py
layout_detector/VGT_model/layers/losses.py
layout_detector/VGT_model/layers/mask_ops.py
layout_detector/VGT_model/layers/nms.py
layout_detector/VGT_model/layers/roi_align.py
layout_detector/VGT_model/layers/roi_align_rotated.py
layout_detector/VGT_model/layers/rotated_boxes.py
layout_detector/VGT_model/layers/shape_spec.py
layout_detector/VGT_model/layers/wrappers.py
layout_detector/VGT_model/modeling/__init__.py
layout_detector/VGT_model/modeling/anchor_generator.py
layout_detector/VGT_model/modeling/box_regression.py
layout_detector/VGT_model/modeling/matcher.py
layout_detector/VGT_model/modeling/poolers.py
layout_detector/VGT_model/modeling/postprocessing.py
layout_detector/VGT_model/modeling/backbone/__init__.py
layout_detector/VGT_model/modeling/backbone/backbone.py
layout_detector/VGT_model/modeling/backbone/fpn.py
layout_detector/VGT_model/modeling/meta_arch/__init__.py
layout_v-0.1.1.dist-info/METADATA
layout_v-0.1.1.dist-info/WHEEL
layout_v-0.1.1.dist-info/top_level.txt
layout_v-0.1.1.dist-info/RECORD
